mkdocs_ansible_collection/__init__.py
mkdocs_ansible_collection/plugin.py
mkdocs_ansible_collection/templates/_templates/environment.md.j2
mkdocs_ansible_collection/templates/collection_index.md.jinja
mkdocs_ansible_collection/templates/default.md.jinja
mkdocs_ansible_collection/templates/plugin.md.jinja
mkdocs_ansible_collection/templates/plugin_list.md.jinja
mkdocs_ansible_collection-1.1.0.dist-info/LICENSE
mkdocs_ansible_collection-1.1.0.dist-info/METADATA
mkdocs_ansible_collection-1.1.0.dist-info/WHEEL
mkdocs_ansible_collection-1.1.0.dist-info/entry_points.txt
mkdocs_ansible_collection-1.1.0.dist-info/RECORD
