Metadata-Version: 2.3
Name: mkdocs-ansible-collection
Version: 1.1.0
Summary: MkDocs Plugin that automatically generates pages for Ansible Collections.
License: MIT
Keywords: mkdocs,ansible
Author: Cristian Sirbu
Author-email: cristian@trueneutral.eu
Requires-Python: >=3.9
Classifier: Intended Audience :: Developers
Classifier: Development Status :: 5 - Production/Stable
Classifier: License :: OSI Approved :: MIT License
Classifier: Operating System :: OS Independent
Classifier: Programming Language :: Python :: 3
Classifier: Programming Language :: Python :: 3.9
Classifier: Programming Language :: Python :: 3.10
Classifier: Programming Language :: Python :: 3.11
Classifier: Programming Language :: Python :: 3.12
Classifier: Programming Language :: Python :: 3.13
Classifier: Topic :: Documentation
Classifier: Topic :: Text Processing
Requires-Dist: ansible-core (>=2.15,<3.0)
Requires-Dist: mkdocs (>=1.6.0,<2.0.0)
Project-URL: Documentation, https://mkdocs-ansible-collection.readthedocs.io/en/latest/
Project-URL: Homepage, https://mkdocs-ansible-collection.readthedocs.io/en/latest/
Project-URL: Repository, https://github.com/cmsirbu/mkdocs-ansible-collection
